vokativ/__init__.py
vokativ/vokativ.py
vokativ/data/man_suffixes
vokativ/data/man_vs_woman_suffixes
vokativ/data/woman_first_vs_last_name_suffixes
vokativ/tests/__init__.py
vokativ/tests/all.py
vokativ-1.2.1.dist-info/LICENSE
vokativ-1.2.1.dist-info/METADATA
vokativ-1.2.1.dist-info/WHEEL
vokativ-1.2.1.dist-info/top_level.txt
vokativ-1.2.1.dist-info/RECORD
