Metadata-Version: 2.1
Name: vokativ
Version: 1.2.1
Summary: Declension of Czech names into vocative case.
Home-page: https://github.com/Mimino666/vokativ
Author: Michal Mimino Danilak
Author-email: michal.danilak@gmail.com
License: MIT
Keywords: czech name vocative vokativ jmena ceska
Platform: UNKNOWN
Classifier: Development Status :: 5 - Production/Stable
Classifier: License :: OSI Approved :: MIT License
Classifier: Natural Language :: Czech
Classifier: Operating System :: OS Independent
Classifier: Programming Language :: Python
Classifier: Programming Language :: Python :: 2
Classifier: Programming Language :: Python :: 2.7
Classifier: Programming Language :: Python :: 3
Classifier: Programming Language :: Python :: 3.5
Classifier: Programming Language :: Python :: 3.6
Classifier: Programming Language :: Python :: 3.7
Classifier: Programming Language :: Python :: 3.8
Classifier: Topic :: Utilities
Requires-Dist: six
